PyTok/__init__.py
PyTok/example.py
PyTok-1.0.0.dist-info/LICENSE
PyTok-1.0.0.dist-info/METADATA
PyTok-1.0.0.dist-info/WHEEL
PyTok-1.0.0.dist-info/top_level.txt
PyTok-1.0.0.dist-info/RECORD
