Metadata-Version: 2.1
Name: PyTok
Version: 1.0.0
Summary: Unoffiical Python 3 TikTok API Wrapper.
Home-page: https://github.com/JohnTheGod/PyTok
Author: John Sandoval
Author-email: johnrobertsandoval@gmail.com
Project-URL: Bug Tracker, https://github.com/JohnTheGod/PyTok/issues
Classifier: Programming Language :: Python :: 3
Classifier: License :: OSI Approved :: MIT License
Classifier: Operating System :: OS Independent
Requires-Python: >=3.6
License-File: LICENSE
